Workbook
Name RateTable: 'Rate Table'!$A$4:$B$23
Name RoleList: 'Rate Table'!$A$4:$A$23

Sheet How to fill
A1: AI Initiative Impact Model — team workbook (all figures in INR)
A3: How this works | B3: Each team fills in ONE copy of this workbook for its initiative. You only touch the 'Inputs' tab and the coloured cells. The 'P&L' tab then shows your initiative's financial impact automatically. The organizer collates every team's P&L into a central leaderboard separately — your numbers are not shared with other teams.
A4: THE KEY ASSUMPTION — full deployment | B4: Assess impact as if your tool is FULLY DEPLOYED to every relevant resource in the company. If it is a design tool, assume the entire design team uses it; if it is a support tool, assume all support agents use it. Enter that full headcount in the Time-saved table. This keeps every team's impact measured on the same basis.
A5: Currency | B5: Everything is in Indian Rupees (₹). Hourly rates come from the central 'Rate Table' tab.
A6: Colour legend | B6: Blue = you type here (input). Black = automatic formula (do not edit). Green = pulled from the Rate Table. Yellow = a cell the organizer sets.
A8: STRUCTURE OF THE COSTS
A9: Build – fixed (one-time) | B9: One-off costs to create the tool that do NOT scale with how many people use it: core development, design, architecture, one-off licences, security review.
A10: Build – variable (one-time) | B10: One-off costs that DO scale with deployment size: per-seat onboarding, data preparation per team, migration per user.
A11: Running – fixed (annual) | B11: Recurring yearly costs independent of usage volume: platform subscription, base infrastructure, fixed support retainer.
A12: Running – variable (annual) | B12: Recurring yearly costs that scale with usage or headcount: per-user licences, API / token / compute per use, usage-based support.
A14: THE TWO WAYS TO SHOW IMPACT
A15: 1. Time saved → cost saved | B15: The tool removes hours of work. Annual hours saved = headcount × hours saved per person × frequency. Multiply by the loaded cost per hour to get the cost saved per year.
A16: 2. Efficiency → higher revenue | B16: The tool lets the team produce more / convert better / free capacity, generating extra revenue at the same or lower cost. Enter the annual revenue uplift and its margin %; the model counts the margin (profit) as the benefit so it is comparable to costs. Never count the same benefit as both time saved AND revenue.
A18: Team size & cost per hour | B18: Captured in the Time-saved table: each resource group has a full-deployment headcount and a loaded cost per hour (auto-filled from the Rate Table). This is the backbone of the cost-saving calculation.
A19: Working days per year | B19: Set once on the Inputs tab (default 240). Used to annualise any hours entered on a 'per Day' basis.
A21: HEADLINE METRICS (on the P&L tab)
A22: Net annual impact | B22: Total annual benefit (cost saved + revenue margin) minus total annual running cost. The steady-state yearly gain.
A23: Year-1 ROI % | B23: (Total annual benefit − annual running cost − one-time build cost) ÷ (annual running cost + one-time build cost).
A24: Payback (months) | B24: Months for the net monthly benefit to repay the one-time build cost. Blank if net annual impact is not positive.

Sheet Rate Table
A1: Central Rate Table — fully-loaded hourly cost per role (INR)
A2: Organizer fills the yellow rates once with the org's fully-loaded hourly cost (salary + benefits + overhead) in INR. Teams pick a role from this list in the Time-saved table; the rate auto-fills.
A3: Role / Band | B3: Fully-loaded rate (₹/hr) | C3: Notes / basis
A4: Subject Head | B4: 1823 | C4: ₹35,00,000 CTC ÷ 1,920 hrs (240 days × 8 hrs) = ₹1,823/hr
A5: Content Faculty | B5: 781 | C5: ₹15,00,000 CTC ÷ 1,920 hrs (240 days × 8 hrs) = ₹781/hr
A6: Project Coordinator | B6: 417 | C6: ₹8,00,000 CTC ÷ 1,920 hrs (240 days × 8 hrs) = ₹417/hr
A7: DTP | B7: 260 | C7: ₹5,00,000 CTC ÷ 1,920 hrs (240 days × 8 hrs) = ₹260/hr
C8: PLACEHOLDER — replace with your loaded rate
C9: PLACEHOLDER — replace with your loaded rate
C10: PLACEHOLDER — replace with your loaded rate
C11: PLACEHOLDER — replace with your loaded rate
C12: PLACEHOLDER — replace with your loaded rate
C13: PLACEHOLDER — replace with your loaded rate
C14: PLACEHOLDER — replace with your loaded rate

Sheet Inputs
A1: Inputs — fill only the coloured cells. All figures in INR.
A2: Assume FULL deployment: your tool is used by every relevant resource in the company. Enter that full headcount in the Time-saved section.
A4: 1. Initiative details
A5: Initiative / tool name | B5: AI based Question Bank
A6: Team | B6: Team 1
A7: Owner | B7: Lovee Mittal
A8: Short description | B8: Quick Test Creation with AI verification
A9: Confidence in inputs (High/Medium/Low) | B9: Medium
A10: Working days per year (assumption) | B10: 240
A12: 2. Build costs – FIXED (one-time)
A13: One-off costs to create the tool that do not scale with usage: core development, design, architecture, one-off licences, security review.
A14: Cost item | B14: Quantity | C14: Unit cost (₹) | D14: Amount (₹) | E14: Notes / assumption
A15: AI Tool - Claude Code | B15: 1 | C15: 23000 | D15: =N(B15)*N(C15) -> 23000
A16: AI Tool - ElevenLabs | B16: 1 | C16: 19356.48 | D16: =N(B16)*N(C16) -> 19356.48
A17: Employee time - Solution Design, Build & QA | B17: 1 | C17: 3000000 | D17: =N(B17)*N(C17) -> 3000000
D18: =N(B18)*N(C18) -> 0
D19: =N(B19)*N(C19) -> 0
D20: =N(B20)*N(C20) -> 0
A21: Subtotal | D21: =SUM(D15:D20) -> 3042356.5
A23: 3. Build costs – VARIABLE (one-time)
A24: One-off costs that scale with deployment size: per-seat onboarding, data prep per team, migration per user. Tip: set Quantity = full-deployment headcount.
A25: Cost item | B25: Quantity | C25: Unit cost (₹) | D25: Amount (₹) | E25: Notes / assumption
A26: App Testing - AI Model APIs | B26: 1 | C26: 20000 | D26: =N(B26)*N(C26) -> 20000
A27: Per-seat onboarding/training (1 hr × 50 staff) | B27: 55 | C27: 781 | D27: =N(B27)*N(C27) -> 42955 | E27: One Time Cost of Training to use the App
A28: Initial content/data setup & metadata tagging | B28: 1 | C28: 50000 | D28: =N(B28)*N(C28) -> 50000 | E28: AI Model cost to tag questions in metadata
D29: =N(B29)*N(C29) -> 0
D30: =N(B30)*N(C30) -> 0
D31: =N(B31)*N(C31) -> 0
A32: Subtotal | D32: =SUM(D26:D31) -> 112955
A34: 4. Running costs – FIXED (annual)
A35: Recurring yearly costs independent of usage: platform subscription, base infrastructure, fixed support retainer.
A36: Cost item | B36: Quantity | C36: Unit cost (₹) | D36: Amount (₹) | E36: Notes / assumption
A37: AI Tool - Claude Code Subscription (Annual) | B37: 1 | C37: 23000 | D37: =N(B37)*N(C37) -> 23000
A38: AI Tool - ElevenLabs Subscription (Annual) | B38: 1 | C38: 19356.48 | D38: =N(B38)*N(C38) -> 19356.48
A39: Supabase Pro | B39: 1 | C39: 30000 | D39: =N(B39)*N(C39) -> 30000 | E39: Postgress Database to store questions + Storage + Authentication
A40: Vercel Pro (Deployment) | B40: 1 | C40: 23000 | D40: =N(B40)*N(C40) -> 23000 | E40: Hosting and Deployment of App on Cloud
A41: Wiris Mathtype Subscription | B41: 1 | C41: 30000 | D41: =N(B41)*N(C41) -> 30000
D42: =N(B42)*N(C42) -> 0
A43: Subtotal | D43: =SUM(D37:D42) -> 125356.48
A45: 5. Running costs – VARIABLE (annual)
A46: Recurring yearly costs that scale with usage or headcount: per-user licences, API / token / compute, usage-based support.
A47: Cost item | B47: Quantity | C47: Unit cost (₹) | D47: Amount (₹) | E47: Notes / assumption
A48: LLM API/token usage (3 level of QC + aggregator/ Question) | B48: 5000000 | C48: 0.1 | D48: =N(B48)*N(C48) -> 500000 | E48: API cost of 50 Lakhs questions to be Verified by AI, extra tokens as per need to validate/ QC
A49: AWS S3/Supabase Storage (per GB) | B49: 1000 | C49: 20 | D49: =N(B49)*N(C49) -> 20000 | E49: Store question/solution figures in database
A50: SME employee time — manual QC of AI-flagged questions | B50: 57600 | C50: 417 | D50: =C50*B50 -> 24019200 | E50: 30 SMEs × 1,920 hrs/yr = 57,600 hrs; ₹8L CTC ÷ 1,920 hrs = ₹417/hr; covers AI-flagged 20% of 50L questions @ 5 min/question
D51: =N(B51)*N(C51) -> 0
D52: =N(B52)*N(C52) -> 0
D53: =N(B53)*N(C53) -> 0
A54: Subtotal | D54: =SUM(D48:D53) -> 24539200
A56: 6. Impact A – TIME SAVED → cost saved
A57: Enter each resource group at FULL deployment. Annual hours saved = headcount × hours per person × frequency (Day uses working-days/yr, Week×48, Month×12, Year×1). Cost/hr auto-fills from the Rate Table.
A58: Role / resource group | B58: Headcount (full deploy) | C58: Hours saved / person | D58: Period | E58: Annual hours saved | F58: Cost per hour (₹) | G58: Annual cost saved (₹) | H58: Notes
A59: Subject Head | B59: 30 | C59: 6.4 | D59: Day | E59: =N(B59)*N(C59)*IF(D59="Day",$B$10,IF(D59="Week",48,IF(D59="Month",12,IF(D59="Year",1,0)))) -> 46080 | F59: =IFERROR(VLOOKUP(A59,RateTable,2,FALSE()),0) -> 1823 | G59: =E59*F59 -> 84003840 | H59: Manual QC: 3 hrs/test → AI-assisted QC: 30 min/test (AI flags ~80% of questions; human reviews remaining 20% only)
A60: Content Faculty | B60: 90 | C60: 6 | D60: Day | E60: =N(B60)*N(C60)*IF(D60="Day",$B$10,IF(D60="Week",48,IF(D60="Month",12,IF(D60="Year",1,0)))) -> 129600 | F60: =IFERROR(VLOOKUP(A60,RateTable,2,FALSE()),0) -> 781 | G60: =E60*F60 -> 101217600 | H60: Manual video solution recording: 1 day (8 hrs)/100 Questions → AI-generated: 30 min/100 Questions
A61: Project Coordinator | B61: 25 | C61: 3 | D61: Day | E61: =N(B61)*N(C61)*IF(D61="Day",$B$10,IF(D61="Week",48,IF(D61="Month",12,IF(D61="Year",1,0)))) -> 18000 | F61: =IFERROR(VLOOKUP(A61,RateTable,2,FALSE()),0) -> 417 | G61: =E61*F61 -> 7506000
A62: DTP | B62: 90 | C62: 6 | D62: Day | E62: =N(B62)*N(C62)*IF(D62="Day",$B$10,IF(D62="Week",48,IF(D62="Month",12,IF(D62="Year",1,0)))) -> 129600 | F62: =IFERROR(VLOOKUP(A62,RateTable,2,FALSE()),0) -> 260 | G62: =E62*F62 -> 33696000 | H62: Manual typing: 6 hrs/test → Bulk extraction (PDF/Word): 2 min/test
E63: =N(B63)*N(C63)*IF(D63="Day",$B$10,IF(D63="Week",48,IF(D63="Month",12,IF(D63="Year",1,0)))) -> 0 | F63: =IFERROR(VLOOKUP(A63,RateTable,2,FALSE()),0) -> 0 | G63: =E63*F63 -> 0
E64: =N(B64)*N(C64)*IF(D64="Day",$B$10,IF(D64="Week",48,IF(D64="Month",12,IF(D64="Year",1,0)))) -> 0 | F64: =IFERROR(VLOOKUP(A64,RateTable,2,FALSE()),0) -> 0 | G64: =E64*F64 -> 0
A65: Subtotal | B65: =SUM(B59:B64) -> 235 | E65: =SUM(E59:E64) -> 323280 | G65: =SUM(G59:G64) -> 226423440
A67: 7. Impact B – EFFICIENCY → higher revenue
A68: For impact that shows up as extra revenue (more output, better conversion, freed capacity sold) rather than hours saved. Enter annual revenue uplift and its margin %; the model counts the MARGIN as the benefit. Do not double-count anything already captured as time saved.
A69: Efficiency / revenue driver | B69: Quantity / basis | C69: Unit value (₹) | D69: Annual revenue uplift (₹) | E69: Margin % | F69: Annual margin contribution (₹) | G69: Notes
A70: SaaS licensing — AI question paper QC platform sold to external coaching institutes | B70: 50000 | C70: 500 | D70: =N(B70)*N(C70) -> 25000000 | E70: 0.8 | F70: =D70*N(E70) -> 20000000 | G70: 1,000 coaching institutes × 50 papers/yr × ₹500/paper; 80% margin after API, hosting & support costs
D71: =N(B71)*N(C71) -> 0 | F71: =D71*N(E71) -> 0
D72: =N(B72)*N(C72) -> 0 | F72: =D72*N(E72) -> 0
D73: =N(B73)*N(C73) -> 0 | F73: =D73*N(E73) -> 0
D74: =N(B74)*N(C74) -> 0 | F74: =D74*N(E74) -> 0
D75: =N(B75)*N(C75) -> 0 | F75: =D75*N(E75) -> 0
A76: Subtotal | D76: =SUM(D70:D75) -> 25000000 | F76: =SUM(F70:F75) -> 20000000

Sheet P&L
A1: Impact P&L — annual, at full deployment (INR)
A2: All figures pull automatically from the Inputs tab. Annual figures assume the tool is fully deployed to all relevant resources. The organizer collates this P&L across teams.
A4: ANNUAL BENEFIT (at full deployment)
A5: Cost saved – time saved | D5: =Inputs!$G$65 -> 226423440
A6: Margin contribution – efficiency / revenue | D6: =Inputs!$F$76 -> 20000000
A7: Total annual benefit | D7: =D5+D6 -> 246423440
A9: ANNUAL RUNNING COST
A10: Running – fixed | D10: =Inputs!$D$43 -> 125356.48
A11: Running – variable | D11: =Inputs!$D$54 -> 24539200
A12: Total annual running cost | D12: =D10+D11 -> 24664556
A14: ONE-TIME BUILD INVESTMENT
A15: Build – fixed | D15: =Inputs!$D$21 -> 3042356.5
A16: Build – variable | D16: =Inputs!$D$32 -> 112955
A17: Total one-time build cost | D17: =D15+D16 -> 3155311.5
A19: IMPACT METRICS
A20: Net annual impact (benefit − running cost) | D20: =D7-D12 -> 2.2175888e+08
A21: Year-1 net impact (benefit − running − build) | D21: =D7-D12-D17 -> 218603572
A22: Year-1 ROI % | D22: =IF((D12+D17)=0,"",(D7-D12-D17)/(D12+D17)) -> 7.8578221
A23: Steady-state annual ROI % | D23: =IF(D12=0,"",(D7-D12)/D12) -> 8.9909942
A24: Payback period (months) | D24: =IF(D20>0,D17/(D20/12),"") -> 0.17074282
A25: Annual hours saved | D25: =Inputs!$E$65 -> 323280
A26: Headcount impacted (full deployment) | D26: =Inputs!$B$65 -> 235
A28: 3-YEAR VIEW (INR)
B29: Year 0 | C29: Year 1 | D29: Year 2 | E29: Year 3
A30: Build cost | B30: =-D17 -> -3155311.5 | C30: 0 | D30: 0 | E30: 0
A31: Running cost | B31: 0 | C31: =-D12 -> -24664556 | D31: =-D12 -> -24664556 | E31: =-D12 -> -24664556
A32: Benefit | B32: 0 | C32: =D7 -> 246423440 | D32: =D7 -> 246423440 | E32: =D7 -> 246423440
A33: Net cash flow | B33: =SUM(B30:B32) -> -3155311.5 | C33: =SUM(C30:C32) -> 2.2175888e+08 | D33: =SUM(D30:D32) -> 2.2175888e+08 | E33: =SUM(E30:E32) -> 2.2175888e+08
A34: Cumulative net | B34: =B33 -> -3155311.5 | C34: =B34+C33 -> 218603572 | D34: =C34+D33 -> 4.4036246e+08 | E34: =D34+E33 -> 6.6212134e+08

Sheet Example
A1: Worked Example (read-only) — design-team AI tool, full deployment
A2: Illustrative only. A design-assist tool deployed to the whole 20-person design team. Numbers are made up. Shows how the sections flow into the headline metrics.
A3: INPUT — scope
A4: Design team size (full deployment) | B4: 20
A5: Loaded cost per hour – Designer (₹/hr) | B5: 1200
A6: Hours saved per designer per week | B6: 5
A7: Working weeks per year | B7: 48
A8: INPUT — costs
A9: Build – fixed (one-time) | B9: 1500000
A10: Build – variable (one-time) | B10: 300000
A11: Running – fixed (annual) | B11: 600000
A12: Running – variable (annual) | B12: 480000
A13: INPUT — efficiency / revenue
A14: Annual revenue uplift | B14: 2000000
A15: Margin % | B15: 0.4
A16: CALCULATED
A17: Annual hours saved (20 × 5 × 48) | B17: =B4*B6*B7 -> 4800
A18: Cost saved – time (₹) | B18: =B17*B5 -> 5760000
A19: Margin contribution – revenue (₹) | B19: =B14*B15 -> 800000
A20: Total annual benefit (₹) | B20: =B18+B19 -> 6560000
A21: Total annual running cost (₹) | B21: =B11+B12 -> 1080000
A22: Total one-time build cost (₹) | B22: =B9+B10 -> 1800000
A23: Net annual impact (₹) | B23: =B20-B21 -> 5480000
A24: Year-1 ROI % | B24: =(B20-B21-B22)/(B21+B22) -> 1.2777778
A25: Payback (months) | B25: =IF((B20-B21)>0,B22/((B20-B21)/12),"") -> 3.9416058
